jh_client/__init__.py
jh_client/api/__init__.py
jh_client/api/default_api.py
jh_client/api_client.py
jh_client/api_response.py
jh_client/configuration.py
jh_client/exceptions.py
jh_client/models/__init__.py
jh_client/models/authorizations_token_post200_response.py
jh_client/models/authorizations_token_post_request.py
jh_client/models/get200_response.py
jh_client/models/group.py
jh_client/models/groups_name_users_post_request.py
jh_client/models/info_get200_response.py
jh_client/models/info_get200_response_authenticator.py
jh_client/models/info_get200_response_spawner.py
jh_client/models/oauth2_token_post200_response.py
jh_client/models/proxy_patch_request.py
jh_client/models/request_identity.py
jh_client/models/server.py
jh_client/models/service.py
jh_client/models/shutdown_post_request.py
jh_client/models/token.py
jh_client/models/user.py
jh_client/models/users_name_activity_post_request.py
jh_client/models/users_name_activity_post_request_servers.py
jh_client/models/users_name_activity_post_request_servers_server_name.py
jh_client/models/users_name_patch_request.py
jh_client/models/users_name_tokens_post_request.py
jh_client/models/users_post_request.py
jh_client/py.typed
jh_client/rest.py
jh_client-1.4.0.dist-info/METADATA
jh_client-1.4.0.dist-info/WHEEL
jh_client-1.4.0.dist-info/RECORD
